Adder2bit.v
module Adder2bit (input wire X, Y, output wire XandY);
	
	reg result;
	
	always @(*) begin
	
		result = X & Y;
	
	end
	
	assign XandY = result;
	
endmodule

Adder2bit_tb.v
module Adder2bit_tb();
	
	reg X = 0;
	reg Y = 0;
	wire out;
	
	reg clk;
	
	Adder2bit dut (X, Y, out);
	
	initial begin
      //take out next two lines if running on altera
      $dumpfile("Adder2bit_tb.vcd");
      $dumpvars(0, dut);
		clk = 0;
      forever #10 clk = ~clk;
   end
	
	initial begin
      #500 $finish; 
   end
	
	always @(posedge clk) begin
	
		X = 1'b1; #10;
		Y = 1'b1; #10;
		X = 1'b0; #10;
		Y = 1'b0; #10;
	
	end
	
endmodule

simulation/modelsim/Adder2bit_tb.vcd
$date
	Wed Feb 05 20:23:38 2020
$end
$version
	ModelSim Version 10.1d
$end
$timescale
	1ps
$end
$scope module Adder2bit_tb $end
$scope module dut $end
$var wire 1 ! X $end
$var wire 1 " Y $end
$var wire 1 # XandY $end
$var reg 1 $ result $end
$upscope $end
$upscope $end
$enddefinitions $end
#0
$dumpvars
0$
0#
0"
0!
$end
#10
1!
#20
1"
1$
1#
#30
0!
0$
0#
#40
0"
#70
1!
#80
1"
1$
1#
#90
0!
0$
0#
#100
0"
#130
1!
#140
1"
1$
1#
#150
0!
0$
0#
#160
0"
#190
1!
#200
1"
1$
1#
#210
0!
0$
0#
#220
0"
#250
1!
#260
1"
1$
1#
#270
0!
0$
0#
#280
0"
#310
1!
#320
1"
1$
1#
#330
0!
0$
0#
#340
0"
#370
1!
#380
1"
1$
1#
#390
0!
0$
0#
#400
0"
#430
1!
#440
1"
1$
1#
#450
0!
0$
0#
#460
0"
#490
1!
