Bit_stage.v
module Bit_stage (input x, y, c0, output G, P, s);	

	assign G = x & y;
	assign P = x ^ y;
	assign s = P ^ c0;

endmodule

Bit_stage_tb.v
module Bit_stage_tb;

	reg x, y, c;
	wire G, P, s;
	
	reg clk = 1;
	
	Bit_stage bsdut (x, y, c, G, P, s);
   
   initial begin
      $dumpfile("Bit_stage_tb.vcd");
      $dumpvars(0, bsdut);
      forever #10 clk = ~clk;     
   end

   initial begin
      #500 $finish;
   end
   
   always @(posedge clk) begin
		c = 0;
      x = 0; y = 0; #50;
		x = 0; y = 1; #50;
		x = 1; y = 0; #50;
		x = 1; y = 1; #50;
		
		c = 1;
		x = 0; y = 0; #50;
		x = 0; y = 1; #50;
		x = 1; y = 0; #50;
		x = 1; y = 1; #50;
   end

endmodule

simulation/modelsim/Bit_stage_tb.vcd
$date
	Mon Feb 10 10:43:15 2020
$end
$version
	ModelSim Version 10.1d
$end
$timescale
	1ps
$end
$scope module Bit_stage_tb $end
$scope module bsdut $end
$var wire 1 ! x $end
$var wire 1 " y $end
$var wire 1 # c0 $end
$var wire 1 $ G $end
$var wire 1 % P $end
$var wire 1 & s $end
$upscope $end
$upscope $end
$enddefinitions $end
#0
$dumpvars
0$
0%
0&
0#
0"
0!
$end
#50
1"
1%
1&
#100
1!
0"
#150
1"
0%
1$
0&
#200
1#
0!
0"
1&
0$
#250
1"
1%
0&
#300
1!
0"
#350
1"
0%
1$
1&
#400
0#
0!
0"
0&
0$
#450
1"
1%
1&
