Bit_stage.v
module Bit_stage (input x, y, c0, output G, P, s);	

	assign G = x & y;
	assign P = x ^ y;
	assign s = P ^ c0;

endmodule

Cla_4.v
module Cla_4(input [3:0] x, y, input c0, output G, P, c4, output [3:0] s);
   wire g0;
   wire p0;
   wire g1;
   wire p1;
   wire g2;
   wire p2;
   wire g3;
   wire p3;
   wire c1;
   wire c2;
   wire c3;

   // Send each bit of x and y down to the bit stage cell
   Bit_stage bit_stage1(x[0], y[0], c0, g0, p0, s[0]);
   Bit_stage bit_stage2(x[1], y[1], c1, g1, p1, s[1]);
   Bit_stage bit_stage3(x[2], y[2], c2, g2, p2, s[2]);
   Bit_stage bit_stage4(x[3], y[3], c3, g3, p3, s[3]);

   // Just the equations for the CLA logic from course reader
   //and(P, p0, p1, p2, p3);  
	
	assign P = p0 & p1 & p2 & p3;
   assign G = g3 | (p3 & g2) | (p3 & p2 & g1) | (p3 & p2 & p1 & g0);
   assign c1 = g0 | (p0 & c0);
   assign c2 = g1 | (p1 & g0) | (p1 & p0 & c0);
   assign c3 = g2 | (p2 & g1) | (p2 & p1 & g0) | (p2 & p1 & p0 & c0);
   assign c4 = g3 | (p3 & g2) | (p3 & p2 & g1) | (p3 & p2 & p1 & g0) | (p3 & p2 & p1 & p0 & c0);

   
   
endmodule

Cla_4_tb.v
module Cla_4_tb;

	reg [3:0] x, y;
	reg c0;
	wire G, P, c4;
	wire [3:0] s;
	
	reg clk = 1;
	
	Cla_4 cla4dut (x, y, c0, G, P, c4, s);
   
   initial begin
      $dumpfile("Cla_4_tb.vcd");
      $dumpvars(0, cla4dut);
      forever #10 clk = ~clk;     
   end

   initial begin
      #500 $finish;
   end
   
   always @(posedge clk) begin
		c0 = 0;
      x = 0; y = 0; #50;
		x = 0; y = 1; #50;
		x = 1; y = 0; #50;
		x = 6; y = 9; #50;
		
		c0 = 1;
		x = 0; y = 0; #50;
		x = 0; y = 1; #50;
		x = 1; y = 0; #50;
		x = 1; y = 1; #50;
   end

endmodule

simulation/modelsim/Cla_4_tb.vcd
$date
	Mon Feb 10 10:54:23 2020
$end
$version
	ModelSim Version 10.1d
$end
$timescale
	1ps
$end
$scope module Cla_4_tb $end
$scope module cla4dut $end
$var wire 1 ! x [3] $end
$var wire 1 " x [2] $end
$var wire 1 # x [1] $end
$var wire 1 $ x [0] $end
$var wire 1 % y [3] $end
$var wire 1 & y [2] $end
$var wire 1 ' y [1] $end
$var wire 1 ( y [0] $end
$var wire 1 ) c0 $end
$var wire 1 * G $end
$var wire 1 + P $end
$var wire 1 , c4 $end
$var wire 1 - s [3] $end
$var wire 1 . s [2] $end
$var wire 1 / s [1] $end
$var wire 1 0 s [0] $end
$var wire 1 1 g0 $end
$var wire 1 2 p0 $end
$var wire 1 3 g1 $end
$var wire 1 4 p1 $end
$var wire 1 5 g2 $end
$var wire 1 6 p2 $end
$var wire 1 7 g3 $end
$var wire 1 8 p3 $end
$var wire 1 9 c1 $end
$var wire 1 : c2 $end
$var wire 1 ; c3 $end
$scope module bit_stage1 $end
$var wire 1 $ x $end
$var wire 1 ( y $end
$var wire 1 ) c0 $end
$var wire 1 1 G $end
$var wire 1 2 P $end
$var wire 1 0 s $end
$upscope $end
$scope module bit_stage2 $end
$var wire 1 # x $end
$var wire 1 ' y $end
$var wire 1 9 c0 $end
$var wire 1 3 G $end
$var wire 1 4 P $end
$var wire 1 / s $end
$upscope $end
$scope module bit_stage3 $end
$var wire 1 " x $end
$var wire 1 & y $end
$var wire 1 : c0 $end
$var wire 1 5 G $end
$var wire 1 6 P $end
$var wire 1 . s $end
$upscope $end
$scope module bit_stage4 $end
$var wire 1 ! x $end
$var wire 1 % y $end
$var wire 1 ; c0 $end
$var wire 1 7 G $end
$var wire 1 8 P $end
$var wire 1 - s $end
$upscope $end
$upscope $end
$upscope $end
$enddefinitions $end
#0
$dumpvars
0*
0+
0,
00
0/
0.
0-
01
02
03
04
05
06
07
08
09
0:
0;
0)
0(
0'
0&
0%
0$
0#
0"
0!
$end
#50
1(
12
10
#100
0(
1$
#150
1(
1%
0$
1#
1"
18
14
16
1+
1-
1/
1.
#200
1)
0(
0%
0#
0"
1,
1;
1:
19
00
02
08
04
06
0,
0;
0:
09
0+
10
0-
0.
0/
#250
1(
12
19
00
1/
#300
0(
1$
#350
1(
02
11
10
#400
0)
0(
0$
00
01
09
0/
#450
1(
12
10
